Workbook

Sheet Dashboard
A1: Insurance Policy Portfolio Dashboard
A4: TOTAL POLICIES | C4: TOTAL CUSTOMERS | E4: TOTAL PREMIUM ($) | G4: TOTAL COVERAGE ($) | I4: TOTAL CLAIMS ($) | K4: TOTAL CLAIMS COUNT | M4: ACTIVE POLICY RATE | O4: AVG RISK SCORE | Q4: AVG PREMIUM ($) | S4: CLAIM APPROVAL RATE
A5: =COUNTA('Policy Details'!A2:A5001) -> 5000 | C5: =COUNTA('Customer Information'!A2:A5001) -> 5000 | E5: =SUM('Policy Details'!D2:D5001) -> 5261008.4 | G5: =SUM('Policy Details'!C2:C5001) -> 1272814747 | I5: =SUM(Claims!C2:C5001) -> 251378846 | K5: =COUNTA(Claims!A2:A5001) -> 5000 | M5: =COUNTIF('Policy Details'!H2:H5001,"Active")/COUNTA('Policy Details'!A2:A5001) -> 0.3364 | O5: =AVERAGE('Additional Fields'!D2:D5001) -> 50.3846 | Q5: =AVERAGE('Policy Details'!D2:D5001) -> 1052.2017 | S5: =COUNTIF(Claims!D2:D5001,"Approved")/COUNTA(Claims!A2:A5001) -> 0.3424
A7: Portfolio Breakdown

Sheet Customer Information
A1: Customer ID | B1: Name | C1: Gender | D1: Age | E1: Occupation | F1: Marital Status | G1: Address (City, State, Zip Code)
A2: CUST87425473 | B2: Norma Fisher | C2: Female | D2: 63 | E2: Futures trader | F2: Married | G2: Sullivanport, New Mexico, 47431
A3: CUST52762998 | B3: Susan Wagner | C3: Male | D3: 57 | E3: Herbalist | F3: Single | G3: Port Cody, Kentucky, 70305
A4: CUST78641469 | B4: Dr. Stephanie Collins | C4: Other | D4: 79 | E4: Buyer, retail | F4: Widowed | G4: Thomasville, Minnesota, 57408
A5: CUST82850738 | B5: Martin Harris | C5: Other | D5: 18 | E5: Sub | F5: Widowed | G5: Ramoshaven, Kentucky, 08664
A6: CUST83770928 | B6: Kimberly Smith | C6: Male | D6: 75 | E6: Oceanographer | F6: Single | G6: New Tristanmouth, Kansas, 96220
A7: CUST03591575 | B7: Seth Lee | C7: Other | D7: 44 | E7: Tax inspector | F7: Divorced | G7: East Linda, Georgia, 71671
A8: CUST45352116 | B8: Bobby Flores | C8: Other | D8: 51 | E8: Rural practice surveyor | F8: Widowed | G8: Rodriguezside, Maine, 93111
A9: CUST06110068 | B9: Gary Nielsen | C9: Other | D9: 68 | E9: Engineer, electronics | F9: Divorced | G9: Seanfurt, Massachusetts, 75952
A10: CUST52268424 | B10: Clinton Underwood | C10: Other | D10: 63 | E10: Amenity horticulturist | F10: Single | G10: Thomasland, Utah, 99801
A11: CUST31531027 | B11: Chase Johnson | C11: Female | D11: 39 | E11: Catering manager | F11: Divorced | G11: Masseyhaven, Louisiana, 68893
A12: CUST40782869 | B12: Sarah Jacobson | C12: Other | D12: 27 | E12: Theme park manager | F12: Single | G12: Rileymouth, New York, 87040
A13: CUST11810816 | B13: Melody Haas | C13: Male | D13: 41 | E13: Marketing executive | F13: Single | G13: West Chloefort, Pennsylvania, 83095
... A5001: CUST37983734 | B5001: Kevin Gonzalez | C5001: Female | D5001: 27 | E5001: Meteorologist | F5001: Divorced | G5001: South Jenniferland, New Hampshire, 67912

Sheet Policy Details
A1: Policy ID | B1: Policy Type | C1: Coverage Amount | D1: Premium Amount | E1: Policy Start Date | F1: Policy End Date | G1: Payment Frequency | H1: Status | I1: Customer ID
A2: POL27806251 | B2: Property | C2: 436672 | D2: 1273.79 | E2: 43461 | F2: 45525 | G2: Monthly | H2: Lapsed | I2: CUST55344519
A3: POL96934398 | B3: Auto | C3: 102437 | D3: 1556.75 | E3: 44442 | F3: 45506 | G3: Monthly | H3: Terminated | I3: CUST71194311
A4: POL93505220 | B4: Auto | C4: 88101 | D4: 886.53 | E4: 43130 | F4: 46025 | G4: Monthly | H4: Lapsed | I4: CUST58699451
A5: POL39531025 | B5: Property | C5: 459915 | D5: 197.75 | E5: 44654 | F5: 48259 | G5: Quarterly | H5: Terminated | I5: CUST72186583
A6: POL38769300 | B6: Health | C6: 22098 | D6: 868.51 | E6: 44471 | F6: 46648 | G6: Quarterly | H6: Active | I6: CUST04808502
A7: POL07841878 | B7: Health | C7: 347514 | D7: 1931.83 | E7: 44091 | F7: 46262 | G7: Monthly | H7: Active | I7: CUST47527169
A8: POL21963992 | B8: Property | C8: 288036 | D8: 247.04 | E8: 43186 | F8: 43681 | G8: Monthly | H8: Active | I8: CUST57892719
A9: POL64589705 | B9: Health | C9: 394231 | D9: 152.13 | E9: 45457 | F9: 45995 | G9: Quarterly | H9: Terminated | I9: CUST97231935
A10: POL49133977 | B10: Property | C10: 148162 | D10: 1383.65 | E10: 42100 | F10: 43731 | G10: Quarterly | H10: Terminated | I10: CUST67080051
A11: POL80278196 | B11: Life | C11: 376522 | D11: 1546.14 | E11: 44136 | F11: 46560 | G11: Quarterly | H11: Lapsed | I11: CUST45705025
A12: POL89935970 | B12: Property | C12: 499740 | D12: 1488.73 | E12: 44246 | F12: 46730 | G12: Quarterly | H12: Active | I12: CUST47003736
A13: POL40425029 | B13: Life | C13: 413248 | D13: 279.96 | E13: 44415 | F13: 45463 | G13: Monthly | H13: Active | I13: CUST15756529
... A5001: POL16711858 | B5001: Property | C5001: 343604 | D5001: 393.1 | E5001: 44534 | F5001: 47830 | G5001: Monthly | H5001: Terminated | I5001: CUST90434699

Sheet Claims
A1: Claim ID | B1: Date of Claim | C1: Claim Amount | D1: Claim Status | E1: Reason for Claim | F1: Settlement Date | G1: Policy ID
A2: CLM77924411 | B2: 45505 | C2: 54655 | D2: Approved | E2: Song member cover lose effect wall walk. | F2: 45516 | G2: POL56612277
A3: CLM28779034 | B3: 45295 | C3: 94225 | D3: Pending | E3: Mean model toward might main maintain. | F3: 45339 | G3: POL69932027
A4: CLM42025979 | B4: 45381 | C4: 17652 | D4: Approved | E4: Day outside produce easy. | G4: POL42688275
A5: CLM69566101 | B5: 44930 | C5: 69929 | D5: Approved | E5: Start after receive daughter newspaper change. | F5: 44981 | G5: POL66279716
A6: CLM58620367 | B6: 44764 | C6: 96366 | D6: Approved | E6: Policy yet yes improve draw some. | G6: POL77439955
A7: CLM07454489 | B7: 44014 | C7: 63905 | D7: Denied | E7: Success move worker among. | F7: 44065 | G7: POL64965934
A8: CLM27552701 | B8: 44592 | C8: 61121 | D8: Pending | E8: Professor four degree feeling person author cell. | F8: 44610 | G8: POL73019543
A9: CLM77756278 | B9: 44795 | C9: 12547 | D9: Pending | E9: Science own thing from class senior provide. | F9: 44837 | G9: POL19552952
A10: CLM05146130 | B10: 44162 | C10: 57203 | D10: Denied | E10: Together mouth various child cultural. | G10: POL07805552
A11: CLM19272700 | B11: 44084 | C11: 62916 | D11: Approved | E11: Both remain note instead first probably. | F11: 44145 | G11: POL88177917
A12: CLM85060604 | B12: 44289 | C12: 79536 | D12: Denied | E12: Company raise drive. | F12: 44304 | G12: POL71221796
A13: CLM86056395 | B13: 44930 | C13: 21469 | D13: Denied | E13: Church option sometimes pick their arm century. | F13: 45001 | G13: POL61467343
A14: CLM98463712 | B14: 44903 | C14: 65329 | D14: Denied | E14: Shake age official become season. | F14: 44928 | G14: POL62363777
A15: CLM98579912 | B15: 45446 | C15: 80670 | D15: Pending | E15: Seek political threat about join determine. | F15: 45467 | G15: POL50374708
A16: CLM90637957 | B16: 44216 | C16: 45282 | D16: Pending | E16: Network bit someone strong mention. | F16: 44271 | G16: POL88242759
A17: CLM12125464 | B17: 45325 | C17: 50353 | D17: Denied | E17: Window above operation perhaps teach east world bit. | F17: 45343 | G17: POL27437608
A18: CLM45720439 | B18: 45049 | C18: 39427 | D18: Denied | E18: Scientist account cover central song. | F18: 45111 | G18: POL77019254
A19: CLM50141230 | B19: 44554 | C19: 43102 | D19: Pending | E19: Always crime indeed idea back. | G19: POL72656147
A20: CLM97150673 | B20: 45523 | C20: 35473 | D20: Pending | E20: Center without look hundred difference writer most. | F20: 45553 | G20: POL19255943
A21: CLM51837945 | B21: 44691 | C21: 13146 | D21: Approved | E21: While operation interview determine let movement. | F21: 44740 | G21: POL85518381
A22: CLM82967170 | B22: 44637 | C22: 2324 | D22: Pending | E22: Option mean marriage news wait major. | F22: 44657 | G22: POL32845970
A23: CLM62837956 | B23: 43959 | C23: 36126 | D23: Denied | E23: Agent several by century quality dream above. | G23: POL95370014
A24: CLM53724406 | B24: 43851 | C24: 80226 | D24: Approved | E24: Director benefit movie want increase shake stage. | G24: POL45794212
A25: CLM16412694 | B25: 44910 | C25: 32102 | D25: Approved | E25: Nothing body who stand. | F25: 44971 | G25: POL61653642
A26: CLM51625573 | B26: 45276 | C26: 31862 | D26: Pending | E26: Only bill later huge. | F26: 45304 | G26: POL93167566
A27: CLM51036457 | B27: 45089 | C27: 25719 | D27: Denied | E27: Water reduce shoulder technology knowledge discussion network then. | F27: 45143 | G27: POL67872849
A28: CLM04762722 | B28: 44060 | C28: 3571 | D28: Approved | E28: Accept billion sure peace hold meeting. | F28: 44079 | G28: POL61884063
A29: CLM43338826 | B29: 45440 | C29: 80190 | D29: Denied | E29: Myself none late. | F29: 45483 | G29: POL89077589
A30: CLM66194342 | B30: 44935 | C30: 56151 | D30: Denied | E30: Bill few morning executive old. | F30: 45021 | G30: POL23806593
A31: CLM27235742 | B31: 44191 | C31: 83640 | D31: Denied | E31: Act new real know live. | G31: POL29474046
A32: CLM02888122 | B32: 44028 | C32: 9836 | D32: Pending | E32: Rule special Democrat million. | F32: 44060 | G32: POL96504333
A33: CLM23673303 | B33: 43839 | C33: 22275 | D33: Pending | E33: Send ok soldier end. | F33: 43902 | G33: POL81591533
A34: CLM98491523 | B34: 45301 | C34: 77913 | D34: Approved | E34: Month station thing police level. | F34: 45318 | G34: POL01681251
A35: CLM20286630 | B35: 44269 | C35: 39165 | D35: Denied | E35: According plan week peace officer particularly. | G35: POL13181377
A36: CLM66676001 | B36: 44530 | C36: 90112 | D36: Approved | E36: Anyone national speak protect professor process station. | F36: 44565 | G36: POL43969785
A37: CLM16206090 | B37: 44045 | C37: 18632 | D37: Denied | E37: Indeed particular keep feeling allow individual. | G37: POL34180846
A38: CLM93705007 | B38: 45132 | C38: 35200 | D38: Approved | E38: Again evidence yourself somebody light already. | F38: 45182 | G38: POL21441518
A39: CLM86984670 | B39: 44514 | C39: 31749 | D39: Denied | E39: Eat among change goal. | F39: 44524 | G39: POL64544270
A40: CLM90814794 | B40: 45359 | C40: 7435 | D40: Denied | E40: Great near boy success. | F40: 45420 | G40: POL54561530
A41: CLM55030421 | B41: 45257 | C41: 76501 | D41: Pending | E41: Education themselves see letter remember unit director. | F41: 45329 | G41: POL95768809
A42: CLM38868037 | B42: 44079 | C42: 90208 | D42: Pending | E42: American material style through evidence southern deep. | G42: POL96685286
A43: CLM09669839 | B43: 44210 | C43: 84492 | D43: Denied | E43: Sign human long air already federal peace art. | F43: 44291 | G43: POL82401042
A44: CLM18327776 | B44: 43834 | C44: 51746 | D44: Approved | E44: Find where back sea program fear. | F44: 43856 | G44: POL03461173
A45: CLM60097748 | B45: 44505 | C45: 21838 | D45: Pending | E45: Deal service agent already improve style. | F45: 44577 | G45: POL59179996
A46: CLM57112717 | B46: 44502 | C46: 28629 | D46: Approved | E46: Two second say if tough voice. | G46: POL23145476
A47: CLM65938667 | B47: 45140 | C47: 80531 | D47: Denied | E47: Movie so writer price rise tell old. | F47: 45152 | G47: POL82016751
A48: CLM14071810 | B48: 44822 | C48: 73972 | D48: Pending | E48: Head mission number natural model. | F48: 44895 | G48: POL09137788
A49: CLM56509285 | B49: 44878 | C49: 53398 | D49: Pending | E49: Crime speak fill step. | F49: 44907 | G49: POL70419372
A50: CLM11001484 | B50: 44284 | C50: 62327 | D50: Denied | E50: Group top woman everyone quickly question majority. | G50: POL90801398
A51: CLM65918046 | B51: 44101 | C51: 30879 | D51: Pending | E51: Doctor especially today value become term identify. | G51: POL82791377
A52: CLM81536271 | B52: 44811 | C52: 18231 | D52: Pending | E52: Year else front than choice. | F52: 44862 | G52: POL15877374
A53: CLM14776484 | B53: 45080 | C53: 33327 | D53: Approved | E53: Why alone its open upon. | G53: POL59779212
A54: CLM33580673 | B54: 45046 | C54: 89459 | D54: Denied | E54: Both series shoulder specific offer language traditional. | G54: POL07342539
A55: CLM37236202 | B55: 45519 | C55: 10248 | D55: Denied | E55: Staff next movie page drop. | F55: 45562 | G55: POL41037493
A56: CLM51134239 | B56: 45026 | C56: 86284 | D56: Pending | E56: Fast team dark century strategy hit. | F56: 45077 | G56: POL82137065
A57: CLM36331542 | B57: 45627 | C57: 47685 | D57: Pending | E57: Seek send believe western chair usually. | G57: POL90934498
A58: CLM68935390 | B58: 44384 | C58: 4745 | D58: Approved | E58: Gas black evidence. | G58: POL83133699
A59: CLM05192558 | B59: 44970 | C59: 64302 | D59: Approved | E59: Own would fire. | G59: POL01761052
A60: CLM34252551 | B60: 44122 | C60: 48742 | D60: Approved | E60: Give computer keep form research despite. | G60: POL08643765
A61: CLM82206005 | B61: 44416 | C61: 48335 | D61: Pending | E61: Adult conference safe poor its industry coach. | G61: POL25617891
A62: CLM25855066 | B62: 44443 | C62: 78981 | D62: Pending | E62: Economy whose same miss national. | F62: 44496 | G62: POL08689656
A63: CLM66661573 | B63: 44892 | C63: 85396 | D63: Denied | E63: Simply charge partner poor with. | F63: 44972 | G63: POL64120254
A64: CLM79682557 | B64: 44739 | C64: 91925 | D64: Denied | E64: Often bring five. | F64: 44803 | G64: POL45114954
A65: CLM70589989 | B65: 44640 | C65: 38297 | D65: Approved | E65: Wonder piece wait look true no remember if. | F65: 44727 | G65: POL63517748
A66: CLM31815501 | B66: 44668 | C66: 66148 | D66: Pending | E66: Several produce class customer alone. | F66: 44748 | G66: POL91259489
A67: CLM63185712 | B67: 44533 | C67: 12659 | D67: Approved | E67: Former table finish boy single practice. | F67: 44586 | G67: POL39463277
A68: CLM23146150 | B68: 45283 | C68: 65025 | D68: Pending | E68: Education shoulder hand father production order choice. | F68: 45310 | G68: POL75706298
A69: CLM01553708 | B69: 45470 | C69: 66661 | D69: Approved | E69: Sound be certainly fly picture space. | F69: 45495 | G69: POL33049382
A70: CLM66074257 | B70: 45636 | C70: 7273 | D70: Denied | E70: Sound that operation avoid morning their. | G70: POL63440106
A71: CLM50724959 | B71: 45515 | C71: 4529 | D71: Denied | E71: Simple other role not. | F71: 45605 | G71: POL59354713
A72: CLM33888157 | B72: 44174 | C72: 54069 | D72: Pending | E72: Response it six realize doctor. | G72: POL77625425
A73: CLM51474654 | B73: 45035 | C73: 10870 | D73: Pending | E73: Staff carry address. | F73: 45084 | G73: POL18831547
A74: CLM93171228 | B74: 45592 | C74: 67443 | D74: Approved | E74: Theory window see soon. | F74: 45629 | G74: POL24534591
A75: CLM43392789 | B75: 43872 | C75: 4636 | D75: Denied | E75: Natural tell whole scientist why weight receive. | F75: 43900 | G75: POL54483538
A76: CLM88894585 | B76: 44127 | C76: 11566 | D76: Approved | E76: One foreign space whether mother. | F76: 44185 | G76: POL55300155
A77: CLM07858710 | B77: 45362 | C77: 23913 | D77: Denied | E77: Kitchen talk throw. | F77: 45381 | G77: POL82812319
A78: CLM97170433 | B78: 44408 | C78: 23354 | D78: Approved | E78: Prevent we project hit oil church. | F78: 44429 | G78: POL33244868
A79: CLM31270051 | B79: 44704 | C79: 94795 | D79: Approved | E79: Name any option into western final. | F79: 44744 | G79: POL74496346
A80: CLM82267397 | B80: 44269 | C80: 11923 | D80: Pending | E80: Push finally hair. | F80: 44284 | G80: POL18917162
A81: CLM25622565 | B81: 45315 | C81: 20013 | D81: Denied | E81: Would level despite imagine. | F81: 45391 | G81: POL98789630
A82: CLM64484686 | B82: 45068 | C82: 6157 | D82: Approved | E82: Our full outside policy. | F82: 45147 | G82: POL47427298
A83: CLM38705286 | B83: 44232 | C83: 63821 | D83: Denied | E83: Camera start really benefit risk security article. | G83: POL76589663
A84: CLM23146923 | B84: 45127 | C84: 19885 | D84: Approved | E84: Top center exist action. | G84: POL12935594
A85: CLM24301039 | B85: 44139 | C85: 47975 | D85: Denied | E85: While character eat expect. | G85: POL55835566
A86: CLM15657898 | B86: 44676 | C86: 98275 | D86: Denied | E86: Act others many weight. | F86: 44721 | G86: POL91241306
A87: CLM64734849 | B87: 44922 | C87: 7732 | D87: Approved | E87: South detail energy somebody coach. | G87: POL10073827
A88: CLM93105620 | B88: 44199 | C88: 25294 | D88: Denied | E88: Event fund less country special. | F88: 44215 | G88: POL43123760
A89: CLM64154491 | B89: 43950 | C89: 4473 | D89: Pending | E89: These series movement international toward change movie yard. | F89: 43978 | G89: POL45095642
A90: CLM33798304 | B90: 45186 | C90: 28593 | D90: Denied | E90: Newspaper season me. | F90: 45208 | G90: POL81122472
A91: CLM14944933 | B91: 44088 | C91: 96104 | D91: Pending | E91: Instead hit field manager difference face will. | G91: POL95405693
A92: CLM95099823 | B92: 44045 | C92: 65503 | D92: Pending | E92: Him book heart still. | G92: POL20670070
A93: CLM39666392 | B93: 44479 | C93: 65199 | D93: Pending | E93: Ball not yet get apply. | F93: 44495 | G93: POL84424949
A94: CLM25529207 | B94: 44475 | C94: 80432 | D94: Denied | E94: Imagine seat friend office it. | F94: 44527 | G94: POL56083774
A95: CLM45018730 | B95: 44273 | C95: 92471 | D95: Approved | E95: Rule memory around international building national. | F95: 44314 | G95: POL50239325
A96: CLM16989357 | B96: 44015 | C96: 62441 | D96: Pending | E96: Able attention our change section rock usually already. | G96: POL66167857
A97: CLM73336882 | B97: 45486 | C97: 84687 | D97: Approved | E97: Possible water guess million. | G97: POL44119689
A98: CLM98110295 | B98: 44210 | C98: 44110 | D98: Denied | E98: Community dog join brother. | F98: 44274 | G98: POL91286503
A99: CLM49151950 | B99: 45302 | C99: 42149 | D99: Denied | E99: Measure partner professor real trouble enter western president. | G99: POL83969664
A100: CLM62334592 | B100: 44776 | C100: 8683 | D100: Denied | E100: Expert near owner. | G100: POL76937321
...

Sheet Payment History
A1: Payment ID | B1: Date of Payment | C1: Amount Paid | D1: Payment Method | E1: Payment Status | F1: Policy ID
A2: PAY00503494 | B2: 45338 | C2: 1121.13 | D2: Cash | E2: Successful | F2: POL09901587
A3: PAY78887551 | B3: 44945 | C3: 1420.69 | D3: Bank Transfer | E3: Successful | F3: POL73324138
A4: PAY14700139 | B4: 45138 | C4: 490.76 | D4: Cash | E4: Successful | F4: POL71278302
A5: PAY00915248 | B5: 44658 | C5: 1150.59 | D5: Cash | E5: Failed | F5: POL24753734
A6: PAY94123626 | B6: 44778 | C6: 1490.26 | D6: Cash | E6: Failed | F6: POL18290935
A7: PAY53415430 | B7: 45540 | C7: 1318.96 | D7: Credit Card | E7: Failed | F7: POL98372511
A8: PAY84843365 | B8: 45187 | C8: 158.43 | D8: Cash | E8: Failed | F8: POL20843719
A9: PAY97836039 | B9: 45196 | C9: 994.21 | D9: Credit Card | E9: Failed | F9: POL03845436
A10: PAY65075228 | B10: 44965 | C10: 233.3 | D10: Bank Transfer | E10: Successful | F10: POL70775475
A11: PAY17334868 | B11: 45457 | C11: 176.91 | D11: Bank Transfer | E11: Failed | F11: POL23603808
A12: PAY39650460 | B12: 44903 | C12: 513.88 | D12: Cash | E12: Failed | F12: POL52535973
A13: PAY81033711 | B13: 45545 | C13: 380.15 | D13: Credit Card | E13: Failed | F13: POL52256054
... A5001: PAY74470147 | B5001: 45027 | C5001: 186.4 | D5001: Cash | E5001: Successful | F5001: POL54989284

Sheet Additional Fields
A1: Agent ID | B1: Renewal Status | C1: Policy Discounts | D1: Risk Score | E1: Policy ID
A2: AGT43228742 | B2: Not Renewed | C2: 31 | D2: 42 | E2: POL27806251
A3: AGT46808172 | B3: Pending | C3: 12 | D3: 76 | E3: POL96934398
A4: AGT32340750 | B4: Pending | C4: 17 | D4: 5 | E4: POL93505220
A5: AGT68647921 | B5: Not Renewed | C5: 18 | D5: 80 | E5: POL39531025
A6: AGT57092464 | B6: Pending | C6: 28 | D6: 1 | E6: POL38769300
A7: AGT47653967 | B7: Renewed | C7: 25 | D7: 36 | E7: POL07841878
A8: AGT05457971 | B8: Not Renewed | C8: 2 | D8: 99 | E8: POL21963992
A9: AGT63127637 | B9: Not Renewed | C9: 13 | D9: 100 | E9: POL64589705
A10: AGT49332725 | B10: Not Renewed | C10: 7 | D10: 35 | E10: POL49133977
A11: AGT70109277 | B11: Not Renewed | C11: 9 | D11: 64 | E11: POL80278196
A12: AGT41262935 | B12: Pending | C12: 11 | D12: 80 | E12: POL89935970
A13: AGT39802391 | B13: Not Renewed | C13: 14 | D13: 41 | E13: POL40425029
... A5001: AGT29267388 | B5001: Not Renewed | C5001: 25 | D5001: 38 | E5001: POL16711858

Sheet ChartData
A1: Policy Status | B1: Count | D1: Policy Type | E1: Count | F1: Total Premium | H1: Claim Status | I1: Count | J1: Total Amount | L1: Payment Method | M1: Count | O1: Renewal Status | P1: Count | R1: Gender | S1: Count | U1: Marital Status | V1: Count | X1: Payment Frequency | Y1: Count
A2: Active | B2: =COUNTIF('Policy Details'!$H$2:$H$5001,A2) -> 1682 | D2: Property | E2: =COUNTIF('Policy Details'!$B$2:$B$5001,D2) -> 1236 | F2: =SUMIF('Policy Details'!$B$2:$B$5001,D2,'Policy Details'!$D$2:$D$5001) -> 1308148.6 | H2: Approved | I2: =COUNTIF(Claims!$D$2:$D$5001,H2) -> 1712 | J2: =SUMIF(Claims!$D$2:$D$5001,H2,Claims!$C$2:$C$5001) -> 85795878 | L2: Cash | M2: =COUNTIF('Payment History'!$D$2:$D$5001,L2) -> 1744 | O2: Renewed | P2: =COUNTIF('Additional Fields'!$B$2:$B$5001,O2) -> 1668 | R2: Female | S2: =COUNTIF('Customer Information'!$C$2:$C$5001,R2) -> 1640 | U2: Married | V2: =COUNTIF('Customer Information'!$F$2:$F$5001,U2) -> 1255 | X2: Monthly | Y2: =COUNTIF('Policy Details'!$G$2:$G$5001,X2) -> 1640
A3: Lapsed | B3: =COUNTIF('Policy Details'!$H$2:$H$5001,A3) -> 1640 | D3: Auto | E3: =COUNTIF('Policy Details'!$B$2:$B$5001,D3) -> 1214 | F3: =SUMIF('Policy Details'!$B$2:$B$5001,D3,'Policy Details'!$D$2:$D$5001) -> 1250378.9 | H3: Pending | I3: =COUNTIF(Claims!$D$2:$D$5001,H3) -> 1650 | J3: =SUMIF(Claims!$D$2:$D$5001,H3,Claims!$C$2:$C$5001) -> 81752606 | L3: Bank Transfer | M3: =COUNTIF('Payment History'!$D$2:$D$5001,L3) -> 1645 | O3: Pending | P3: =COUNTIF('Additional Fields'!$B$2:$B$5001,O3) -> 1647 | R3: Male | S3: =COUNTIF('Customer Information'!$C$2:$C$5001,R3) -> 1705 | U3: Single | V3: =COUNTIF('Customer Information'!$F$2:$F$5001,U3) -> 1234 | X3: Quarterly | Y3: =COUNTIF('Policy Details'!$G$2:$G$5001,X3) -> 1711
A4: Terminated | B4: =COUNTIF('Policy Details'!$H$2:$H$5001,A4) -> 1678 | D4: Health | E4: =COUNTIF('Policy Details'!$B$2:$B$5001,D4) -> 1316 | F4: =SUMIF('Policy Details'!$B$2:$B$5001,D4,'Policy Details'!$D$2:$D$5001) -> 1363452.5 | H4: Denied | I4: =COUNTIF(Claims!$D$2:$D$5001,H4) -> 1638 | J4: =SUMIF(Claims!$D$2:$D$5001,H4,Claims!$C$2:$C$5001) -> 83830362 | L4: Credit Card | M4: =COUNTIF('Payment History'!$D$2:$D$5001,L4) -> 1611 | O4: Not Renewed | P4: =COUNTIF('Additional Fields'!$B$2:$B$5001,O4) -> 1685 | R4: Other | S4: =COUNTIF('Customer Information'!$C$2:$C$5001,R4) -> 1655 | U4: Widowed | V4: =COUNTIF('Customer Information'!$F$2:$F$5001,U4) -> 1222 | X4: Annually | Y4: =COUNTIF('Policy Details'!$G$2:$G$5001,X4) -> 1649
D5: Life | E5: =COUNTIF('Policy Details'!$B$2:$B$5001,D5) -> 1234 | F5: =SUMIF('Policy Details'!$B$2:$B$5001,D5,'Policy Details'!$D$2:$D$5001) -> 1339028.4 | U5: Divorced | V5: =COUNTIF('Customer Information'!$F$2:$F$5001,U5) -> 1289
A8: Year | B8: Claim Count | C8: Claim Amount | E8: Age Group | F8: Count | H8: Year | I8: New Policies
A9: 2019 | B9: =SUMPRODUCT((YEAR(Claims!$B$2:$B$5001)=A9)*1) -> 20 | C9: =SUMPRODUCT((YEAR(Claims!$B$2:$B$5001)=A9)*Claims!$C$2:$C$5001) -> 937661 | E9: 18-25 | F9: =COUNTIFS('Customer Information'!$D$2:$D$5001,">="&18,'Customer Information'!$D$2:$D$5001,"<="&25) -> 571 | H9: 2019 | I9: =SUMPRODUCT((YEAR('Policy Details'!$E$2:$E$5001)=H9)*1) -> 499
A10: 2020 | B10: =SUMPRODUCT((YEAR(Claims!$B$2:$B$5001)=A10)*1) -> 1011 | C10: =SUMPRODUCT((YEAR(Claims!$B$2:$B$5001)=A10)*Claims!$C$2:$C$5001) -> 52247659 | E10: 26-35 | F10: =COUNTIFS('Customer Information'!$D$2:$D$5001,">="&26,'Customer Information'!$D$2:$D$5001,"<="&35) -> 788 | H10: 2020 | I10: =SUMPRODUCT((YEAR('Policy Details'!$E$2:$E$5001)=H10)*1) -> 508
A11: 2021 | B11: =SUMPRODUCT((YEAR(Claims!$B$2:$B$5001)=A11)*1) -> 986 | C11: =SUMPRODUCT((YEAR(Claims!$B$2:$B$5001)=A11)*Claims!$C$2:$C$5001) -> 49991556 | E11: 36-45 | F11: =COUNTIFS('Customer Information'!$D$2:$D$5001,">="&36,'Customer Information'!$D$2:$D$5001,"<="&45) -> 739 | H11: 2021 | I11: =SUMPRODUCT((YEAR('Policy Details'!$E$2:$E$5001)=H11)*1) -> 496
A12: 2022 | B12: =SUMPRODUCT((YEAR(Claims!$B$2:$B$5001)=A12)*1) -> 1016 | C12: =SUMPRODUCT((YEAR(Claims!$B$2:$B$5001)=A12)*Claims!$C$2:$C$5001) -> 51360349 | E12: 46-55 | F12: =COUNTIFS('Customer Information'!$D$2:$D$5001,">="&46,'Customer Information'!$D$2:$D$5001,"<="&55) -> 740 | H12: 2022 | I12: =SUMPRODUCT((YEAR('Policy Details'!$E$2:$E$5001)=H12)*1) -> 509
A13: 2023 | B13: =SUMPRODUCT((YEAR(Claims!$B$2:$B$5001)=A13)*1) -> 1020 | C13: =SUMPRODUCT((YEAR(Claims!$B$2:$B$5001)=A13)*Claims!$C$2:$C$5001) -> 50673100 | E13: 56-65 | F13: =COUNTIFS('Customer Information'!$D$2:$D$5001,">="&56,'Customer Information'!$D$2:$D$5001,"<="&65) -> 752 | H13: 2023 | I13: =SUMPRODUCT((YEAR('Policy Details'!$E$2:$E$5001)=H13)*1) -> 494
A14: 2024 | B14: =SUMPRODUCT((YEAR(Claims!$B$2:$B$5001)=A14)*1) -> 947 | C14: =SUMPRODUCT((YEAR(Claims!$B$2:$B$5001)=A14)*Claims!$C$2:$C$5001) -> 46168521 | E14: 66-75 | F14: =COUNTIFS('Customer Information'!$D$2:$D$5001,">="&66,'Customer Information'!$D$2:$D$5001,"<="&75) -> 682 | H14: 2024 | I14: =SUMPRODUCT((YEAR('Policy Details'!$E$2:$E$5001)=H14)*1) -> 480
E15: 76-85 | F15: =COUNTIFS('Customer Information'!$D$2:$D$5001,">="&76,'Customer Information'!$D$2:$D$5001,"<="&85) -> 728
